{
  "data": {
    "result": [
      {
        "id": "1",
        "picUrl": "https://fuss10.elemecdn.com/a/3f/3302e58f9a181d2509f3dc0fa68b0jpeg.jpeg",
        "playCount": "11",
        "name": "test"
      },
      {
        "id": "2",
        "picUrl": "https://fuss10.elemecdn.com/a/3f/3302e58f9a181d2509f3dc0fa68b0jpeg.jpeg",
        "playCount": "11",
        "name": "test"
      },
      {
        "id": "3",
        "picUrl": "https://fuss10.elemecdn.com/a/3f/3302e58f9a181d2509f3dc0fa68b0jpeg.jpeg",
        "playCount": "11",
        "name": "test"
      },
      {
        "id": "4",
        "picUrl": "https://fuss10.elemecdn.com/a/3f/3302e58f9a181d2509f3dc0fa68b0jpeg.jpeg",
        "playCount": "11",
        "name": "test"
      },
      {
        "id": "5",
        "picUrl": "https://fuss10.elemecdn.com/a/3f/3302e58f9a181d2509f3dc0fa68b0jpeg.jpeg",
        "playCount": "11",
        "name": "test"
      },
      {
        "id": "6",
        "picUrl": "https://fuss10.elemecdn.com/a/3f/3302e58f9a181d2509f3dc0fa68b0jpeg.jpeg",
        "playCount": "11",
        "name": "test"
      }
    ]
  }
}